{
  "id": "f62833dd-86bc-497e-a8a2-6919a48e0f2e",
  "prevId": "00000000-0000-0000-0000-000000000000",
  "version": "7",
  "dialect": "postgresql",
  "tables": {
    "public.workflow_acls": {
      "name": "workflow_acls",
      "schema": "",
      "columns": {
        "id": {
          "name": "id",
          "type": "uuid",
          "primaryKey": true,
          "notNull": true,
          "default": "gen_random_uuid()"
        },
        "workflow_id": {
          "name": "workflow_id",
          "type": "uuid",
          "primaryKey": false,
          "notNull": true
        },
        "principal_type": {
          "name": "principal_type",
          "type": "principal_type",
          "typeSchema": "public",
          "primaryKey": false,
          "notNull": true
        },
        "principal_id": {
          "name": "principal_id",
          "type": "varchar(255)",
          "primaryKey": false,
          "notNull": true
        },
        "permissions": {
          "name": "permissions",
          "type": "jsonb",
          "primaryKey": false,
          "notNull": true
        },
        "created_by": {
          "name": "created_by",
          "type": "varchar(255)",
          "primaryKey": false,
          "notNull": true
        },
        "created_at": {
          "name": "created_at",
          "type": "timestamp",
          "primaryKey": false,
          "notNull": true,
          "default": "now()"
        }
      },
      "indexes": {
        "workflow_acls_workflow_idx": {
          "name": "workflow_acls_workflow_idx",
          "columns": [
            {
              "expression": "workflow_id",
              "isExpression": false,
              "asc": true,
              "nulls": "last"
            }
          ],
          "isUnique": false,
          "concurrently": false,
          "method": "btree",
          "with": {}
        },
        "workflow_acls_principal_idx": {
          "name": "workflow_acls_principal_idx",
          "columns": [
            {
              "expression": "principal_type",
              "isExpression": false,
              "asc": true,
              "nulls": "last"
            },
            {
              "expression": "principal_id",
              "isExpression": false,
              "asc": true,
              "nulls": "last"
            }
          ],
          "isUnique": false,
          "concurrently": false,
          "method": "btree",
          "with": {}
        }
      },
      "foreignKeys": {
        "workflow_acls_workflow_id_workflows_id_fk": {
          "name": "workflow_acls_workflow_id_workflows_id_fk",
          "tableFrom": "workflow_acls",
          "tableTo": "workflows",
          "columnsFrom": [
            "workflow_id"
          ],
          "columnsTo": [
            "id"
          ],
          "onDelete": "cascade",
          "onUpdate": "no action"
        }
      },
      "compositePrimaryKeys": {},
      "uniqueConstraints": {
        "workflow_acls_workflow_principal_unique": {
          "name": "workflow_acls_workflow_principal_unique",
          "nullsNotDistinct": false,
          "columns": [
            "workflow_id",
            "principal_type",
            "principal_id"
          ]
        }
      },
      "policies": {},
      "checkConstraints": {},
      "isRLSEnabled": false
    },
    "public.workflow_run_events": {
      "name": "workflow_run_events",
      "schema": "",
      "columns": {
        "id": {
          "name": "id",
          "type": "uuid",
          "primaryKey": true,
          "notNull": true,
          "default": "gen_random_uuid()"
        },
        "run_id": {
          "name": "run_id",
          "type": "uuid",
          "primaryKey": false,
          "notNull": true
        },
        "seq": {
          "name": "seq",
          "type": "integer",
          "primaryKey": false,
          "notNull": true
        },
        "t_ms": {
          "name": "t_ms",
          "type": "bigint",
          "primaryKey": false,
          "notNull": true
        },
        "name": {
          "name": "name",
          "type": "varchar(255)",
          "primaryKey": false,
          "notNull": true
        },
        "level": {
          "name": "level",
          "type": "varchar(16)",
          "primaryKey": false,
          "notNull": true,
          "default": "'info'"
        },
        "node_id": {
          "name": "node_id",
          "type": "varchar(255)",
          "primaryKey": false,
          "notNull": false
        },
        "data": {
          "name": "data",
          "type": "jsonb",
          "primaryKey": false,
          "notNull": false
        },
        "created_at": {
          "name": "created_at",
          "type": "timestamp",
          "primaryKey": false,
          "notNull": true,
          "default": "now()"
        }
      },
      "indexes": {
        "workflow_run_events_run_id_idx": {
          "name": "workflow_run_events_run_id_idx",
          "columns": [
            {
              "expression": "run_id",
              "isExpression": false,
              "asc": true,
              "nulls": "last"
            }
          ],
          "isUnique": false,
          "concurrently": false,
          "method": "btree",
          "with": {}
        },
        "workflow_run_events_run_time_idx": {
          "name": "workflow_run_events_run_time_idx",
          "columns": [
            {
              "expression": "run_id",
              "isExpression": false,
              "asc": true,
              "nulls": "last"
            },
            {
              "expression": "t_ms",
              "isExpression": false,
              "asc": true,
              "nulls": "last"
            }
          ],
          "isUnique": false,
          "concurrently": false,
          "method": "btree",
          "with": {}
        }
      },
      "foreignKeys": {
        "workflow_run_events_run_id_workflow_runs_id_fk": {
          "name": "workflow_run_events_run_id_workflow_runs_id_fk",
          "tableFrom": "workflow_run_events",
          "tableTo": "workflow_runs",
          "columnsFrom": [
            "run_id"
          ],
          "columnsTo": [
            "id"
          ],
          "onDelete": "cascade",
          "onUpdate": "no action"
        }
      },
      "compositePrimaryKeys": {},
      "uniqueConstraints": {
        "workflow_run_events_run_seq_unique": {
          "name": "workflow_run_events_run_seq_unique",
          "nullsNotDistinct": false,
          "columns": [
            "run_id",
            "seq"
          ]
        }
      },
      "policies": {},
      "checkConstraints": {},
      "isRLSEnabled": false
    },
    "public.workflow_runs": {
      "name": "workflow_runs",
      "schema": "",
      "columns": {
        "id": {
          "name": "id",
          "type": "uuid",
          "primaryKey": true,
          "notNull": true,
          "default": "gen_random_uuid()"
        },
        "workflow_id": {
          "name": "workflow_id",
          "type": "uuid",
          "primaryKey": false,
          "notNull": true
        },
        "workflow_version_id": {
          "name": "workflow_version_id",
          "type": "uuid",
          "primaryKey": false,
          "notNull": true
        },
        "status": {
          "name": "status",
          "type": "varchar(32)",
          "primaryKey": false,
          "notNull": true,
          "default": "'queued'"
        },
        "trigger": {
          "name": "trigger",
          "type": "jsonb",
          "primaryKey": false,
          "notNull": true,
          "default": "'{}'::jsonb"
        },
        "input": {
          "name": "input",
          "type": "jsonb",
          "primaryKey": false,
          "notNull": false
        },
        "output": {
          "name": "output",
          "type": "jsonb",
          "primaryKey": false,
          "notNull": false
        },
        "error": {
          "name": "error",
          "type": "jsonb",
          "primaryKey": false,
          "notNull": false
        },
        "correlation_id": {
          "name": "correlation_id",
          "type": "varchar(255)",
          "primaryKey": false,
          "notNull": false
        },
        "idempotency_key": {
          "name": "idempotency_key",
          "type": "varchar(255)",
          "primaryKey": false,
          "notNull": false
        },
        "created_by_user_id": {
          "name": "created_by_user_id",
          "type": "varchar(255)",
          "primaryKey": false,
          "notNull": false
        },
        "started_at": {
          "name": "started_at",
          "type": "timestamp",
          "primaryKey": false,
          "notNull": false
        },
        "ended_at": {
          "name": "ended_at",
          "type": "timestamp",
          "primaryKey": false,
          "notNull": false
        },
        "duration_ms": {
          "name": "duration_ms",
          "type": "integer",
          "primaryKey": false,
          "notNull": false
        },
        "created_at": {
          "name": "created_at",
          "type": "timestamp",
          "primaryKey": false,
          "notNull": true,
          "default": "now()"
        }
      },
      "indexes": {
        "workflow_runs_workflow_id_idx": {
          "name": "workflow_runs_workflow_id_idx",
          "columns": [
            {
              "expression": "workflow_id",
              "isExpression": false,
              "asc": true,
              "nulls": "last"
            }
          ],
          "isUnique": false,
          "concurrently": false,
          "method": "btree",
          "with": {}
        },
        "workflow_runs_workflow_status_idx": {
          "name": "workflow_runs_workflow_status_idx",
          "columns": [
            {
              "expression": "workflow_id",
              "isExpression": false,
              "asc": true,
              "nulls": "last"
            },
            {
              "expression": "status",
              "isExpression": false,
              "asc": true,
              "nulls": "last"
            }
          ],
          "isUnique": false,
          "concurrently": false,
          "method": "btree",
          "with": {}
        },
        "workflow_runs_created_at_idx": {
          "name": "workflow_runs_created_at_idx",
          "columns": [
            {
              "expression": "created_at",
              "isExpression": false,
              "asc": true,
              "nulls": "last"
            }
          ],
          "isUnique": false,
          "concurrently": false,
          "method": "btree",
          "with": {}
        },
        "workflow_runs_correlation_id_idx": {
          "name": "workflow_runs_correlation_id_idx",
          "columns": [
            {
              "expression": "correlation_id",
              "isExpression": false,
              "asc": true,
              "nulls": "last"
            }
          ],
          "isUnique": false,
          "concurrently": false,
          "method": "btree",
          "with": {}
        },
        "workflow_runs_idempotency_key_idx": {
          "name": "workflow_runs_idempotency_key_idx",
          "columns": [
            {
              "expression": "idempotency_key",
              "isExpression": false,
              "asc": true,
              "nulls": "last"
            }
          ],
          "isUnique": false,
          "concurrently": false,
          "method": "btree",
          "with": {}
        }
      },
      "foreignKeys": {
        "workflow_runs_workflow_id_workflows_id_fk": {
          "name": "workflow_runs_workflow_id_workflows_id_fk",
          "tableFrom": "workflow_runs",
          "tableTo": "workflows",
          "columnsFrom": [
            "workflow_id"
          ],
          "columnsTo": [
            "id"
          ],
          "onDelete": "cascade",
          "onUpdate": "no action"
        },
        "workflow_runs_workflow_version_id_workflow_versions_id_fk": {
          "name": "workflow_runs_workflow_version_id_workflow_versions_id_fk",
          "tableFrom": "workflow_runs",
          "tableTo": "workflow_versions",
          "columnsFrom": [
            "workflow_version_id"
          ],
          "columnsTo": [
            "id"
          ],
          "onDelete": "restrict",
          "onUpdate": "no action"
        }
      },
      "compositePrimaryKeys": {},
      "uniqueConstraints": {},
      "policies": {},
      "checkConstraints": {},
      "isRLSEnabled": false
    },
    "public.workflow_tasks": {
      "name": "workflow_tasks",
      "schema": "",
      "columns": {
        "id": {
          "name": "id",
          "type": "uuid",
          "primaryKey": true,
          "notNull": true,
          "default": "gen_random_uuid()"
        },
        "run_id": {
          "name": "run_id",
          "type": "uuid",
          "primaryKey": false,
          "notNull": true
        },
        "node_id": {
          "name": "node_id",
          "type": "varchar(255)",
          "primaryKey": false,
          "notNull": true
        },
        "type": {
          "name": "type",
          "type": "varchar(32)",
          "primaryKey": false,
          "notNull": true,
          "default": "'approval'"
        },
        "status": {
          "name": "status",
          "type": "varchar(32)",
          "primaryKey": false,
          "notNull": true,
          "default": "'open'"
        },
        "assigned_to": {
          "name": "assigned_to",
          "type": "jsonb",
          "primaryKey": false,
          "notNull": true,
          "default": "'{}'::jsonb"
        },
        "prompt": {
          "name": "prompt",
          "type": "jsonb",
          "primaryKey": false,
          "notNull": false
        },
        "decision": {
          "name": "decision",
          "type": "jsonb",
          "primaryKey": false,
          "notNull": false
        },
        "created_by_user_id": {
          "name": "created_by_user_id",
          "type": "varchar(255)",
          "primaryKey": false,
          "notNull": false
        },
        "decided_by_user_id": {
          "name": "decided_by_user_id",
          "type": "varchar(255)",
          "primaryKey": false,
          "notNull": false
        },
        "decided_at": {
          "name": "decided_at",
          "type": "timestamp",
          "primaryKey": false,
          "notNull": false
        },
        "expires_at": {
          "name": "expires_at",
          "type": "timestamp",
          "primaryKey": false,
          "notNull": false
        },
        "created_at": {
          "name": "created_at",
          "type": "timestamp",
          "primaryKey": false,
          "notNull": true,
          "default": "now()"
        }
      },
      "indexes": {
        "workflow_tasks_run_id_idx": {
          "name": "workflow_tasks_run_id_idx",
          "columns": [
            {
              "expression": "run_id",
              "isExpression": false,
              "asc": true,
              "nulls": "last"
            }
          ],
          "isUnique": false,
          "concurrently": false,
          "method": "btree",
          "with": {}
        },
        "workflow_tasks_status_idx": {
          "name": "workflow_tasks_status_idx",
          "columns": [
            {
              "expression": "status",
              "isExpression": false,
              "asc": true,
              "nulls": "last"
            }
          ],
          "isUnique": false,
          "concurrently": false,
          "method": "btree",
          "with": {}
        },
        "workflow_tasks_run_status_idx": {
          "name": "workflow_tasks_run_status_idx",
          "columns": [
            {
              "expression": "run_id",
              "isExpression": false,
              "asc": true,
              "nulls": "last"
            },
            {
              "expression": "status",
              "isExpression": false,
              "asc": true,
              "nulls": "last"
            }
          ],
          "isUnique": false,
          "concurrently": false,
          "method": "btree",
          "with": {}
        }
      },
      "foreignKeys": {
        "workflow_tasks_run_id_workflow_runs_id_fk": {
          "name": "workflow_tasks_run_id_workflow_runs_id_fk",
          "tableFrom": "workflow_tasks",
          "tableTo": "workflow_runs",
          "columnsFrom": [
            "run_id"
          ],
          "columnsTo": [
            "id"
          ],
          "onDelete": "cascade",
          "onUpdate": "no action"
        }
      },
      "compositePrimaryKeys": {},
      "uniqueConstraints": {},
      "policies": {},
      "checkConstraints": {},
      "isRLSEnabled": false
    },
    "public.workflow_versions": {
      "name": "workflow_versions",
      "schema": "",
      "columns": {
        "id": {
          "name": "id",
          "type": "uuid",
          "primaryKey": true,
          "notNull": true,
          "default": "gen_random_uuid()"
        },
        "workflow_id": {
          "name": "workflow_id",
          "type": "uuid",
          "primaryKey": false,
          "notNull": true
        },
        "version": {
          "name": "version",
          "type": "integer",
          "primaryKey": false,
          "notNull": true
        },
        "status": {
          "name": "status",
          "type": "varchar(32)",
          "primaryKey": false,
          "notNull": true,
          "default": "'draft'"
        },
        "definition": {
          "name": "definition",
          "type": "jsonb",
          "primaryKey": false,
          "notNull": true,
          "default": "'{}'::jsonb"
        },
        "created_by_user_id": {
          "name": "created_by_user_id",
          "type": "varchar(255)",
          "primaryKey": false,
          "notNull": true
        },
        "created_at": {
          "name": "created_at",
          "type": "timestamp",
          "primaryKey": false,
          "notNull": true,
          "default": "now()"
        }
      },
      "indexes": {
        "workflow_versions_workflow_id_idx": {
          "name": "workflow_versions_workflow_id_idx",
          "columns": [
            {
              "expression": "workflow_id",
              "isExpression": false,
              "asc": true,
              "nulls": "last"
            }
          ],
          "isUnique": false,
          "concurrently": false,
          "method": "btree",
          "with": {}
        },
        "workflow_versions_workflow_status_idx": {
          "name": "workflow_versions_workflow_status_idx",
          "columns": [
            {
              "expression": "workflow_id",
              "isExpression": false,
              "asc": true,
              "nulls": "last"
            },
            {
              "expression": "status",
              "isExpression": false,
              "asc": true,
              "nulls": "last"
            }
          ],
          "isUnique": false,
          "concurrently": false,
          "method": "btree",
          "with": {}
        }
      },
      "foreignKeys": {
        "workflow_versions_workflow_id_workflows_id_fk": {
          "name": "workflow_versions_workflow_id_workflows_id_fk",
          "tableFrom": "workflow_versions",
          "tableTo": "workflows",
          "columnsFrom": [
            "workflow_id"
          ],
          "columnsTo": [
            "id"
          ],
          "onDelete": "cascade",
          "onUpdate": "no action"
        }
      },
      "compositePrimaryKeys": {},
      "uniqueConstraints": {
        "workflow_versions_workflow_version_unique": {
          "name": "workflow_versions_workflow_version_unique",
          "nullsNotDistinct": false,
          "columns": [
            "workflow_id",
            "version"
          ]
        }
      },
      "policies": {},
      "checkConstraints": {},
      "isRLSEnabled": false
    },
    "public.workflows": {
      "name": "workflows",
      "schema": "",
      "columns": {
        "id": {
          "name": "id",
          "type": "uuid",
          "primaryKey": true,
          "notNull": true,
          "default": "gen_random_uuid()"
        },
        "name": {
          "name": "name",
          "type": "varchar(255)",
          "primaryKey": false,
          "notNull": true
        },
        "slug": {
          "name": "slug",
          "type": "varchar(255)",
          "primaryKey": false,
          "notNull": true
        },
        "description": {
          "name": "description",
          "type": "text",
          "primaryKey": false,
          "notNull": false
        },
        "owner_user_id": {
          "name": "owner_user_id",
          "type": "varchar(255)",
          "primaryKey": false,
          "notNull": true
        },
        "created_at": {
          "name": "created_at",
          "type": "timestamp",
          "primaryKey": false,
          "notNull": true,
          "default": "now()"
        },
        "updated_at": {
          "name": "updated_at",
          "type": "timestamp",
          "primaryKey": false,
          "notNull": true,
          "default": "now()"
        }
      },
      "indexes": {
        "workflows_slug_idx": {
          "name": "workflows_slug_idx",
          "columns": [
            {
              "expression": "slug",
              "isExpression": false,
              "asc": true,
              "nulls": "last"
            }
          ],
          "isUnique": false,
          "concurrently": false,
          "method": "btree",
          "with": {}
        },
        "workflows_owner_user_id_idx": {
          "name": "workflows_owner_user_id_idx",
          "columns": [
            {
              "expression": "owner_user_id",
              "isExpression": false,
              "asc": true,
              "nulls": "last"
            }
          ],
          "isUnique": false,
          "concurrently": false,
          "method": "btree",
          "with": {}
        }
      },
      "foreignKeys": {},
      "compositePrimaryKeys": {},
      "uniqueConstraints": {
        "workflows_slug_unique": {
          "name": "workflows_slug_unique",
          "nullsNotDistinct": false,
          "columns": [
            "slug"
          ]
        }
      },
      "policies": {},
      "checkConstraints": {},
      "isRLSEnabled": false
    }
  },
  "enums": {
    "public.principal_type": {
      "name": "principal_type",
      "schema": "public",
      "values": [
        "user",
        "group",
        "role",
        "location",
        "division",
        "department"
      ]
    }
  },
  "schemas": {},
  "sequences": {},
  "roles": {},
  "policies": {},
  "views": {},
  "_meta": {
    "columns": {},
    "schemas": {},
    "tables": {}
  }
}